agenticle/__init__.py
agenticle/agent.py
agenticle/dashboard.py
agenticle/event.py
agenticle/group.py
agenticle/mcp.py
agenticle/model.py
agenticle/mutilmodal.py
agenticle/optimizer.py
agenticle/schema.py
agenticle/server.py
agenticle/tool.py
agenticle/prompts/brainstorm_prompt.md
agenticle/prompts/competition_opt_prompt.md
agenticle/prompts/default_agent_prompt.md
agenticle/prompts/format_prompt.md
agenticle/prompts/opt_prompt.md
agenticle/prompts/tool_call.md
agenticle/service/__init__.py
agenticle/service/openai_compat.py
agenticle/utils/__init__.py
agenticle/utils/parser.py
tests/__init__.py
tests/test_hierarchical_delegation.py
tests/test_manager_delegation.py
tests/test_model_loader.py
tests/test_modelize.py
tests/test_round_robin.py
tests/test_state_management.py
tests/test_voting.py
tests/utils.py
agenticle-0.1.4.dist-info/METADATA
agenticle-0.1.4.dist-info/WHEEL
agenticle-0.1.4.dist-info/top_level.txt
agenticle-0.1.4.dist-info/RECORD
