Metadata-Version: 2.4
Name: agenticle
Version: 0.1.4
Summary: A lightweight, extensible Python framework for building and orchestrating single or multi-agent AI systems. | 一个轻量、可扩展的 Python 框架，用于构建和编排单智能体或多智能体 AI 系统。
Author-email: A03HCY <acdphc@qq.com>
Project-URL: Homepage, https://github.com/A03HCY/AgentFrame
Project-URL: Bug Tracker, https://github.com/A03HCY/AgentFrame/issues
Classifier: Programming Language :: Python :: 3
Classifier: License :: OSI Approved :: MIT License
Classifier: Operating System :: OS Independent
Requires-Python: >=3.8
Requires-Dist: openai
Requires-Dist: jinja2
Requires-Dist: sseclient
Requires-Dist: requests
Requires-Dist: pyyaml
Requires-Dist: fastapi
Requires-Dist: uvicorn
